<?xml version="1.0" ?>
<ExportAPERO>
     <OrientationConique>
          <OrIntImaM2C>
               <I00>0 0</I00>
               <V10>1 0</V10>
               <V01>0 1</V01>
          </OrIntImaM2C>
          <TypeProj>eProjStenope</TypeProj>
          <ZoneUtileInPixel>true</ZoneUtileInPixel>
          <FileInterne>Ori-Calib/AutoCal_Foc-4000_Cam-Sequoia.xml</FileInterne>
          <RelativeNameFI>true</RelativeNameFI>
          <Externe>
               <AltiSol>-10.8450029976346549</AltiSol>
               <Profondeur>9.50046966446543451</Profondeur>
               <Time>-1.00000000000000002e+30</Time>
               <KnownConv>eConvApero_DistM2C</KnownConv>
               <Centre>-0.0164141366703051614 -0.44062108669470873 0.209339145894714029</Centre>
               <IncCentre>1 1 1</IncCentre>
               <ParamRotation>
                    <CodageMatr>
                         <L1>0.876061581405109036 -0.459270555003901126 0.146924003799202896</L1>
                         <L2>-0.454687133002749877 -0.888245675631111786 -0.0654158299218889627</L2>
                         <L3>0.160548175535317722 -0.00949615864644700117 -0.986982323196946787</L3>
                    </CodageMatr>
               </ParamRotation>
          </Externe>
          <Verif>
               <Tol>0.00100000000000000002</Tol>
               <ShowMes>true</ShowMes>
               <Appuis>
                    <Num>0</Num>
                    <Im>214.560758526697043 547.663879121857804</Im>
                    <Ter>-1.90174834376371948 0.140669561203498772 -7.87538542821128562</Ter>
               </Appuis>
               <Appuis>
                    <Num>1</Num>
                    <Im>232.962591005304432 621.251506202143219</Im>
                    <Ter>-1.70799983817769419 -0.430483243205322996 -6.54525606537197735</Ter>
               </Appuis>
               <Appuis>
                    <Num>2</Num>
                    <Im>726.757446526880244 207.596371196709811</Im>
                    <Ter>2.24186681588796111 0.440865159040429944 -5.94172200044105736</Ter>
               </Appuis>
               <Appuis>
                    <Num>3</Num>
                    <Im>150.242524835303925 341.140112810341748</Im>
                    <Ter>-1.44727427934313635 1.53350821830094297 -6.7850475668077932</Ter>
               </Appuis>
               <Appuis>
                    <Num>4</Num>
                    <Im>1003.52866338704519 791.77630724244807</Im>
                    <Ter>2.31270387088454843 -3.94540316472739949 -6.14646326990554037</Ter>
               </Appuis>
               <Appuis>
                    <Num>5</Num>
                    <Im>1159.44206451347213 118.567896123420724</Im>
                    <Ter>8.71808056971703849 -0.0625371614711208168 -8.91228223324018387</Ter>
               </Appuis>
               <Appuis>
                    <Num>6</Num>
                    <Im>254.645615124552819 493.975009910192568</Im>
                    <Ter>-0.915762352120548684 0.0713206885941273794 -4.97966272944373145</Ter>
               </Appuis>
               <Appuis>
                    <Num>7</Num>
                    <Im>639.758872721579564 309.630981042564827</Im>
                    <Ter>1.77550019399824355 0.217881261359700373 -7.31723728441021226</Ter>
               </Appuis>
               <Appuis>
                    <Num>8</Num>
                    <Im>626.345596350585083 32.7774188693190922</Im>
                    <Ter>4.9638656320946879 4.47618901832762539 -13.4826347658043986</Ter>
               </Appuis>
               <Appuis>
                    <Num>9</Num>
                    <Im>536.091628467885471 709.013174718525761</Im>
                    <Ter>-0.401455145523165413 -3.199212024685131 -13.0340351893828235</Ter>
               </Appuis>
          </Verif>
          <ConvOri>
               <KnownConv>eConvApero_DistM2C</KnownConv>
          </ConvOri>
     </OrientationConique>
</ExportAPERO>
